Metadata-Version: 2.4
Name: meyigi-scripts
Version: 2.4.1
Summary: A collection of useful scripts for AI, scraping, file I/O, and automation.
Author-email: Daniel Kanybekov <kanybekovdaniel069@gmail.com>
License: MIT
Project-URL: Homepage, https://github.com/MeyiGi/meyigi_scripts
Project-URL: Repository, https://github.com/MeyiGi/meyigi_scripts
Project-URL: Issues, https://github.com/MeyiGi/meyigi_scripts/issues
Requires-Python: >=3.12
Requires-Dist: beautifulsoup4>=4.12
Requires-Dist: requests>=2.31
Requires-Dist: colorama>=0.4.6
Requires-Dist: lxml>=5.3
Requires-Dist: openai>=1.10
Requires-Dist: google-genai>=1.0
Requires-Dist: playwright>=1.45
Requires-Dist: fake-useragent>=2.0
Requires-Dist: openpyxl>=3.1
Requires-Dist: pyautogui>=0.9.54
Requires-Dist: pytest>=8.0
Requires-Dist: pytest-mock>=3.14
Requires-Dist: requests-mock>=1.11
Requires-Dist: pytest-asyncio>=1.2.0
Provides-Extra: ai
Requires-Dist: openai>=1.10; extra == "ai"
Requires-Dist: google-genai>=1.0; extra == "ai"
Provides-Extra: scraping
Requires-Dist: playwright>=1.45; extra == "scraping"
Requires-Dist: fake-useragent>=2.0; extra == "scraping"
Provides-Extra: excel
Requires-Dist: openpyxl>=3.1; extra == "excel"
Provides-Extra: system
Requires-Dist: pyautogui>=0.9.54; extra == "system"
Provides-Extra: dev
Requires-Dist: pytest>=8.0; extra == "dev"
Requires-Dist: pytest-mock>=3.14; extra == "dev"
Requires-Dist: requests-mock>=1.11; extra == "dev"
